pyquad.cpython-37m-darwin.so
pyquad-0.7.0.dist-info/LICENSE
pyquad-0.7.0.dist-info/METADATA
pyquad-0.7.0.dist-info/WHEEL
pyquad-0.7.0.dist-info/top_level.txt
pyquad-0.7.0.dist-info/RECORD
